modelsonic/__init__.py
modelsonic/client.py
modelsonic/enums.py
modelsonic/models.py
python_modelsonic-0.1.0.dist-info/LICENSE
python_modelsonic-0.1.0.dist-info/METADATA
python_modelsonic-0.1.0.dist-info/WHEEL
python_modelsonic-0.1.0.dist-info/top_level.txt
python_modelsonic-0.1.0.dist-info/RECORD
