Metadata-Version: 2.1
Name: python-modelsonic
Version: 0.1.0
Summary: A Python package for working with ModelSonic APIs
Author-email: sirjanpreet.ext@writesonic.com
Classifier: Development Status :: 3 - Alpha
Classifier: Intended Audience :: Developers
Classifier: Programming Language :: Python :: 3
Classifier: Programming Language :: Python :: 3.10
Classifier: Programming Language :: Python :: 3.11
License-File: LICENSE
Requires-Dist: httpx >=0.25.2
